dialectal_arabic_tools/__init__.py
dialectal_arabic_tools/cli.py
dialectal_arabic_tools/dialectal_arabic_tools.py
dialectal_arabic_tools/segmentation.py
dialectal_arabic_tools/data/example.in.txt
dialectal_arabic_tools/data/example.out.txt
dialectal_arabic_tools/data/seg_keras_model_0922.hdf5
dialectal_arabic_tools-0.0.1a9.dist-info/DESCRIPTION.rst
dialectal_arabic_tools-0.0.1a9.dist-info/METADATA
dialectal_arabic_tools-0.0.1a9.dist-info/RECORD
dialectal_arabic_tools-0.0.1a9.dist-info/WHEEL
dialectal_arabic_tools-0.0.1a9.dist-info/entry_points.txt
dialectal_arabic_tools-0.0.1a9.dist-info/metadata.json
dialectal_arabic_tools-0.0.1a9.dist-info/top_level.txt
dialectal_arabic_tools-0.0.1a9.dist-info/zip-safe
