Metadata-Version: 2.0
Name: dialectal-arabic-tools
Version: 0.0.1a9
Summary: Dialectal Arabic Tools comprises the different modules developed in Qatar Computing Research Institute (QCRI) developed by the ALT team to handle Dialectal Arabic Segmentation, POS tagging, daicrtization and more
Home-page: https://github.com/qcri/dialectal_arabic_tools
Author: Mohamed Eldesouki
Author-email: disooqi@gmail.com
License: UNKNOWN
Keywords: dialectal_arabic_tools
Platform: UNKNOWN
Classifier: Development Status :: 2 - Pre-Alpha
Classifier: Intended Audience :: Developers
Classifier: Natural Language :: English
Classifier: Programming Language :: Python :: 2.7
Classifier: Programming Language :: Python :: 3.5
Classifier: Programming Language :: Python :: 3.6
Requires-Dist: Click (>=6.0)
Requires-Dist: h5py
Requires-Dist: numpy
Requires-Dist: tensorflow
